fds/__init__.py
fds/sdk/__init__.py
fds/sdk/FactSetGlobalPrices/__init__.py
fds/sdk/FactSetGlobalPrices/api_client.py
fds/sdk/FactSetGlobalPrices/configuration.py
fds/sdk/FactSetGlobalPrices/exceptions.py
fds/sdk/FactSetGlobalPrices/model_utils.py
fds/sdk/FactSetGlobalPrices/rest.py
fds/sdk/FactSetGlobalPrices/api/__init__.py
fds/sdk/FactSetGlobalPrices/api/batch_processing_api.py
fds/sdk/FactSetGlobalPrices/api/corporate_actions_api.py
fds/sdk/FactSetGlobalPrices/api/corporate_actions_for_calendar_api.py
fds/sdk/FactSetGlobalPrices/api/market_value_api.py
fds/sdk/FactSetGlobalPrices/api/prices_api.py
fds/sdk/FactSetGlobalPrices/api/returns_api.py
fds/sdk/FactSetGlobalPrices/api/shares_outstanding_api.py
fds/sdk/FactSetGlobalPrices/apis/__init__.py
fds/sdk/FactSetGlobalPrices/model/__init__.py
fds/sdk/FactSetGlobalPrices/model/adjust.py
fds/sdk/FactSetGlobalPrices/model/annualized_dividend_response.py
fds/sdk/FactSetGlobalPrices/model/annualized_dividends_object.py
fds/sdk/FactSetGlobalPrices/model/annualized_dividends_request.py
fds/sdk/FactSetGlobalPrices/model/batch.py
fds/sdk/FactSetGlobalPrices/model/batch_error_object.py
fds/sdk/FactSetGlobalPrices/model/batch_error_object_links.py
fds/sdk/FactSetGlobalPrices/model/batch_error_response.py
fds/sdk/FactSetGlobalPrices/model/batch_result.py
fds/sdk/FactSetGlobalPrices/model/batch_result_response.py
fds/sdk/FactSetGlobalPrices/model/batch_status.py
fds/sdk/FactSetGlobalPrices/model/batch_status_response.py
fds/sdk/FactSetGlobalPrices/model/calendar.py
fds/sdk/FactSetGlobalPrices/model/cancelled_dividend.py
fds/sdk/FactSetGlobalPrices/model/corporate_action.py
fds/sdk/FactSetGlobalPrices/model/corporate_action_calendar.py
fds/sdk/FactSetGlobalPrices/model/corporate_actions_request.py
fds/sdk/FactSetGlobalPrices/model/corporate_actions_response.py
fds/sdk/FactSetGlobalPrices/model/corporate_actions_response_calendar.py
fds/sdk/FactSetGlobalPrices/model/dividend_adjust.py
fds_sdk_factsetglobalprices-2.5.1.dist-info/licenses/LICENSE
fds_sdk_factsetglobalprices-2.5.1.dist-info/METADATA
fds_sdk_factsetglobalprices-2.5.1.dist-info/WHEEL
fds_sdk_factsetglobalprices-2.5.1.dist-info/top_level.txt
fds_sdk_factsetglobalprices-2.5.1.dist-info/RECORD
